{
  "labels": {
    "洋室": [
      [
        [
          8.0,
          9.0
        ],
        [
          12.0,
          389.0
        ],
        [
          201.0,
          388.0
        ],
        [
          202.0,
          261.0
        ],
        [
          270.0,
          267.0
        ],
        [
          267.0,
          200.0
        ],
        [
          197.0,
          197.0
        ],
        [
          201.0,
          5.0
        ]
      ],
      [
        [
          262.0,
          199.0
        ],
        [
          585.0,
          199.0
        ],
        [
          585.0,
          392.0
        ],
        [
          262.0,
          392.0
        ]
      ]
    ],
    "廊下": [
      [
        [
          204.0,
          132.0
        ],
        [
          452.0,
          132.0
        ],
        [
          452.0,
          198.0
        ],
        [
          204.0,
          198.0
        ]
      ]
    ],
    "開戸": [
      [
        401.90697674418607,
        120.3953488372093,
        447.06976744186045,
        184.95348837209298
      ],
      [
        462.0287769784172,
        139.0,
        512.0,
        220.76978417266184
      ],
      [
        199.0,
        181.0,
        264.0,
        258.0
      ],
      [
        265.71942446043164,
        173.28776978417264,
        319.5827338129496,
        256.31654676258995
      ],
      [
        145.51162790697674,
        141.41860465116278,
        218.76744186046514,
        193.65116279069767
      ]
    ],
    "折戸": [
      [
        170.6618705035971,
        14.719424460431668,
        221.63309352517987,
        130.84172661870502
      ]
    ],
    "引戸": [
      [
        185.0,
        265.74418604651163,
        221.09302325581396,
        380.0
      ],
      [
        436.2093023255814,
        94.23255813953489,
        469.34883720930236,
        191.32558139534885
      ]
    ]
  }
}