{
  "labels": {
    "廊下": [
      [
        [
          180.0,
          45.0
        ],
        [
          176.0,
          265.0
        ],
        [
          508.0,
          263.0
        ],
        [
          510.0,
          157.0
        ],
        [
          840.0,
          161.0
        ],
        [
          838.0,
          273.0
        ],
        [
          1004.0,
          271.0
        ],
        [
          1002.0,
          43.0
        ]
      ]
    ],
    "洋室": [
      [
        [
          950.0,
          267.0
        ],
        [
          944.0,
          495.0
        ],
        [
          1054.0,
          487.0
        ],
        [
          1054.0,
          713.0
        ],
        [
          1384.0,
          723.0
        ],
        [
          1390.0,
          275.0
        ],
        [
          1108.0,
          277.0
        ],
        [
          1110.0,
          155.0
        ],
        [
          998.0,
          157.0
        ],
        [
          1004.0,
          271.0
        ]
      ],
      [
        [
          670.0,
          267.0
        ],
        [
          948.0,
          267.0
        ],
        [
          948.0,
          711.0
        ],
        [
          670.0,
          711.0
        ]
      ],
      [
        [
          398.0,
          267.0
        ],
        [
          668.0,
          267.0
        ],
        [
          668.0,
          711.0
        ],
        [
          398.0,
          711.0
        ]
      ]
    ],
    "開戸": [
      [
        416.0,
        231.88888888888886,
        497.99999999999994,
        353.0
      ],
      [
        852.6296296296296,
        232.81481481481478,
        941.2222222222223,
        355.0
      ],
      [
        973.9259259259259,
        166.37037037037038,
        1088.7407407407409,
        263.3703703703703
      ],
      [
        918.3333333333334,
        44.85185185185185,
        1033.1851851851852,
        152.07407407407408
      ]
    ],
    "折戸": [
      [
        521.1481481481482,
        232.81481481481478,
        660.037037037037,
        295.77777777777777
      ],
      [
        907.2592592592592,
        504.1111111111111,
        969.2962962962962,
        695.1481481481482
      ],
      [
        679.4814814814814,
        124.48148148148147,
        826.7037037037037,
        182.8148148148148
      ]
    ]
  }
}